[
    {
        "id": 1,
        "name": "Master Painting",
        "price": 250,
        "img": "../images/painting/painting1.jpg",
        "status": ""
    },
    {
        "id": 2,
        "name": "Farstol Painting",
        "price": "135",
        "img": "../images/painting/painting2.jpg",
        "status": ""
    },
    {
        "id": 3,
        "name": "Farstol Painting",
        "price": 155,
        "img": "../images/painting/painting3.jpg",
        "status": "sale"
    },
    {
        "id": 4,
        "name": "Sundarban Painting",
        "price": 170,
        "img": "../images/painting/painting4.jpg",
        "status": ""
    },
    {
        "id": 5,
        "name": "Farstol Painting",
        "price": 220,
        "img": "../images/painting/painting5.jpg",
        "status": ""
    },
    {
        "id": 6,
        "name": "Ancient Painting",
        "price": 120,
        "img": "../images/painting/painting6.jpg",
        "status": "sale"
    },
    {
        "id": 7,
        "name": "Ocean Painting",
        "price": 150,
        "img": "../images/painting/painting7.jpg",
        "status": ""
    },
    {
        "id": 8,
        "name": "Farstol Painting",
        "price": 190,
        "img": "../images/painting/painting8.jpg",
        "status": "sale"
    }
]